Metadata-Version: 2.2
Name: mpyfileopt
Version: 1.0.1
Summary: Efficient MicroPython Device File System Management Tool
Home-page: https://github.com/emofalling/MpyFileOpt-Python
Author: emofalling
Author-email: emofalling@dingtalk.com
License: MIT
Keywords: mpyfileopt,mpyfopt,python,micropython,windows,linux,mac,ampy
Classifier: Development Status :: 3 - Alpha
Classifier: License :: OSI Approved :: MIT License
Classifier: Intended Audience :: Developers
Classifier: Programming Language :: Python :: 3.10
Classifier: Programming Language :: Python :: 3.11
Classifier: Programming Language :: Python :: 3.12
Classifier: Programming Language :: Python :: 3.13
Classifier: Programming Language :: Python :: 3.14
Classifier: Operating System :: OS Independent
Requires-Python: >=3.10
License-File: LICENSE
Requires-Dist: pyserial>=3.0
Dynamic: author
Dynamic: author-email
Dynamic: classifier
Dynamic: description
Dynamic: description-content-type
Dynamic: home-page
Dynamic: keywords
Dynamic: license
Dynamic: requires-dist
Dynamic: requires-python
Dynamic: summary
